LICENSE
MANIFEST.in
README.rst
setup.py
transit/__init__.py
transit/_transit.cpp
transit/simple.py
transit/simple_kepler.py
transit/tests.py
transit/transit.py
transit.egg-info/PKG-INFO
transit.egg-info/SOURCES.txt
transit.egg-info/dependency_links.txt
transit.egg-info/top_level.txt
transit/include/ellint.h
transit/include/integrator.h
transit/include/jet_ext.h
transit/include/kepler.h
transit/include/numerical_limb_darkening.h
transit/include/quad.h
transit/include/simple.h
transit/include/ttvfaster.h
transit/include/ceres/fpclassify.h
transit/include/ceres/jet.h