Metadata-Version: 1.1
Name: transit
Version: 0.3.0
Summary: A Python library for computing the light curves of transiting planets
Home-page: http://github.com/dfm/transit
Author: Daniel Foreman-Mackey
Author-email: danfm@nyu.edu
License: MIT
Platform: UNKNOWN
Classifier: Development Status :: 3 - Alpha
Classifier: Intended Audience :: Science/Research
Classifier: License :: OSI Approved :: MIT License
Classifier: Operating System :: OS Independent
Classifier: Programming Language :: Python
